Workbook

Sheet location
A1: locationID | B1: ISO3 | C1: ISO_1 | D1: country_code | E1: location | F1: location_var | G1: gadm1_name | H1: gadm1_var | I1: island | J1: gadm0_name | K1: tdwg4_name | L1: tdwg1 | M1: tdwg1_name | N1: glonaf_country | O1: adm_level | P1: sinas_region | Q1: continent
A2: 1 | B2: ABW | C2: AW | D2: AW | E2: Aruba | I2: 1 | J2: Aruba | K2: Aruba | L2: 8 | M2: Southern America | N2: Aruba | O2: 0 | P2: Central America and the Caribbean | Q2: North America
A3: 2 | B3: AFG | C3: AF | D3: AF | E3: Afghanistan | I3: 0 | J3: Afghanistan | K3: Afghanistan | L3: 3 | M3: Asia-Temperate | N3: Afghanistan | O3: 0 | P3: Western Asia | Q3: Asia
A4: 3 | B4: AGO | C4: AO | D4: AO | E4: Angola | I4: 0 | J4: Angola | K4: Angola | L4: 2 | M4: Africa | N4: Angola | O4: 0 | P4: Sub-Saharan Africa | Q4: Africa
A5: 4 | B5: AIA | C5: AI | D5: AI | E5: Anguilla | F5: Anguilla Island | I5: 1 | J5: Anguilla | K5: Anguilla | L5: 8 | M5: Southern America | N5: Anguilla | O5: 0 | P5: Central America and the Caribbean | Q5: North America
A6: 5 | B6: ALA | C6: AX | D6: AX | E6: Åland | F6: Aland Islands; Åland Islands; �LAND ISLANDS | I6: 1 | J6: Åland | L6: 1 | M6: Europe | O6: 0 | P6: Europe | Q6: Europe
A7: 6 | B7: ALB | C7: AL | D7: AL | E7: Albania | F7: Western Palaearctic Region - Albania | I7: 0 | J7: Albania | K7: Albania | L7: 1 | M7: Europe | N7: Albania | O7: 0 | P7: Europe | Q7: Europe
A8: 7 | B8: AND | C8: AD | D8: AD | E8: Andorra | I8: 0 | J8: Andorra | M8: Europe | O8: 0 | P8: Europe | Q8: Europe
A9: 8 | B9: CUW | C9: CW | D9: CW | E9: Curaçao | F9: Curaçao; Curacao; CuraÃ§ao I.; Curaçao I.; Curacao I. | I9: 1 | J9: Curaçao | K9: Curacao | L9: 8 | M9: Southern America | N9: Netherlands Antilles | O9: 0 | P9: Central America and the Caribbean | Q9: North America
A10: 9 | B10: SXM | C10: SX | D10: SX | E10: Sint Maarten | F10: Sint Maarten (Dutch part); St Maarten (NL) | I10: 1 | J10: Sint Maarten | K10: Netherlands Leeward Is. | L10: 8 | M10: Southern America | N10: Netherlands Antilles | O10: 0 | P10: Central America and the Caribbean | Q10: North America
A11: 10 | B11: ARE | C11: AE | D11: AE | E11: United Arab Emirates | F11: United Arab Em.; the United Arab Emirates | I11: 0 | J11: United Arab Emirates | K11: United Arab Emirates | L11: 3 | M11: Asia-Temperate | N11: United Arab Emirates (the) | O11: 0 | P11: Saharo-Arabia | Q11: Asia
A12: 11 | B12: ARG | C12: AR | D12: AR | E12: Argentina | F12: Argentina Distrito Federal; Argentina Northeast; Argentina Northwest; Argentina South; Argentine | I12: 0 | J12: Argentina | L12: 8 | M12: Southern America | N12: Argentina | O12: 0 | P12: Southern America | Q12: South America
A13: 12 | B13: ARM | C13: AM | D13: AM | E13: Armenia | I13: 0 | J13: Armenia | K13: Armenia | L13: 3 | M13: Asia-Temperate | N13: Armenia | O13: 0 | P13: Western Asia | Q13: Asia
A14: 13 | B14: ASM | C14: AS | D14: AS | E14: American Samoa | I14: 1 | J14: American Samoa | L14: 6 | M14: Pacific | N14: American Samoa | O14: 0 | P14: Pacific | Q14: Oceania
A15: 14 | B15: ATA | C15: AQ | D15: AQ | E15: Antarctica | F15: Brunt Ice Shelf; Adelie Land; East Antarctic Ice Sheet; East Antarctica; Ellsworth Mountains; Enderby Land; Filchner Ice Shelf; Larsen Ice Shelf; North Victoria Land; North-west Antarctic Peninsula; Ross Ice Shelf; South Antarctic Peninsula; South Orkney Islands; South Victoria Land; Transantarctic Mountains | I15: 0 | J15: Antarctica | K15: Antarctica | L15: 9 | M15: Antarctic | N15: Antarctica | O15: 0 | P15: Antarctic | Q15: Antarctica
A16: 15 | B16: ATF | C16: TF | D16: TF | E16: Crozet Islands | F16: Crozet; Crozet Islands Group; Crozet. Is; Îles Crozet; Crozet Is.; Crozet Island Group | I16: 1 | J16: French Southern Territories | L16: 9 | M16: Antarctic | N16: French Southern Territories (the) | O16: 0 | P16: Antarctic | Q16: Antarctica
A17: 16 | B17: ATF | C17: TF | D17: TF | E17: Kerguelen Islands | F17: Kerguelen; Kerguelen Islands (France); Kerguelen Is.; Kerguelen Island | I17: 1 | J17: French Southern Territories | L17: 9 | M17: Antarctic | N17: French Southern Territories (the) | O17: 0 | P17: Antarctic | Q17: Antarctica
A18: 17 | B18: ATF | C18: TF | D18: TF | E18: Scattered Islands | F18: Scattered; Îles Éparses; Glorioso Islands | I18: 1 | J18: French Southern Territories | L18: 9 | M18: Antarctic | N18: French Southern Territories (the) | O18: 0 | P18: Antarctic | Q18: Antarctica
A19: 18 | B19: ATF | C19: TF | D19: TF | E19: St. Paul Island | F19: St Paul I. | I19: 1 | J19: French Southern Territories | L19: 9 | M19: Antarctic | N19: French Southern Territories (the) | O19: 0 | P19: Antarctic | Q19: Antarctica
A20: 19 | B20: ATF | C20: TF | D20: TF | E20: Amsterdam Island | F20: Amsterdam I.; Amsterdam Islands | I20: 1 | J20: French Southern Territories | L20: 9 | M20: Antarctic | N20: French Southern Territories (the) | O20: 0 | P20: Antarctic | Q20: Antarctica
A21: 20 | B21: AUS | C21: AU | D21: AU | E21: Australia | F21: Eastern Australia; South Western Australia; North Western Australia; South Western Australia; Australasian Region - Australia; Autralia | I21: 0 | J21: Australia | L21: 5 | M21: Australasia | N21: Australia | O21: 0 | P21: Australasia | Q21: Oceania
A22: 21 | B22: AUS | C22: AU | D22: AU | E22: Tasmania | F22: Australasian Region - Tasmania; AUSTRALIA Tasmania; Macquarie Island | I22: 1 | J22: Australia | K22: Tasmania | L22: 5 | M22: Australasia | N22: Australia | O22: 0 | P22: Australasia | Q22: Oceania
A23: 22 | B23: AUT | C23: AT | D23: AT | E23: Austria | F23: Western Palaearctic Region - Austria | I23: 0 | J23: Austria | L23: 1 | M23: Europe | N23: Austria | O23: 0 | P23: Europe | Q23: Europe
A24: 23 | B24: AZE | C24: AZ | D24: AZ | E24: Azerbaijan | I24: 0 | J24: Azerbaijan | M24: Asia-Temperate | O24: 0 | P24: Western Asia | Q24: Asia
A25: 24 | B25: BDI | C25: BI | D25: BI | E25: Burundi | I25: 0 | J25: Burundi | K25: Burundi | L25: 2 | M25: Africa | N25: Burundi | O25: 0 | P25: Sub-Saharan Africa | Q25: Africa
A26: 25 | B26: BEL | C26: BE | D26: BE | E26: Belgium | I26: 0 | J26: Belgium | K26: Belgium | L26: 1 | M26: Europe | N26: Belgium | O26: 0 | P26: Europe | Q26: Europe
A27: 26 | B27: BEN | C27: BJ | D27: BJ | E27: Benin | I27: 0 | J27: Benin | K27: Benin | L27: 2 | M27: Africa | N27: Benin | O27: 0 | P27: Sub-Saharan Africa | Q27: Africa
A28: 27 | B28: BES | C28: BQ | D28: BQ | E28: Bonaire | F28: Bonaire (Netherlands) | I28: 1 | J28: Bonaire, Saint Eustatius and Saba | M28: Southern America | O28: 0 | P28: Central America and the Caribbean | Q28: North America
A29: 28 | B29: BES | C29: BQ | D29: BQ | E29: Saba | I29: 1 | J29: Bonaire, Saint Eustatius and Saba | M29: Southern America | O29: 0 | P29: Central America and the Caribbean | Q29: North America
A30: 29 | B30: BES | C30: BQ | D30: BQ | E30: Sint Eustatius | I30: 1 | J30: Bonaire, Saint Eustatius and Saba | M30: Southern America | O30: 0 | P30: Central America and the Caribbean | Q30: North America
A31: 30 | B31: BFA | C31: BF | D31: BF | E31: Burkina Faso | F31: Burkina | I31: 0 | J31: Burkina Faso | K31: Burkina Faso | L31: 2 | M31: Africa | N31: Burkina Faso | O31: 0 | P31: Sub-Saharan Africa | Q31: Africa
A32: 31 | B32: BGD | C32: BD | D32: BD | E32: Bangladesh | I32: 0 | J32: Bangladesh | K32: Bangladesh | L32: 4 | M32: Asia-Tropical | N32: Bangladesh | O32: 0 | P32: Southern Asia | Q32: Asia
A33: 32 | B33: BGR | C33: BG | D33: BG | E33: Bulgaria | I33: 0 | J33: Bulgaria | K33: Bulgaria | L33: 1 | M33: Europe | N33: Bulgaria | O33: 0 | P33: Europe | Q33: Europe
A34: 33 | B34: BHR | C34: BH | D34: BH | E34: Bahrain | I34: 0 | J34: Bahrain | L34: 3 | M34: Asia-Temperate | O34: 0 | P34: Saharo-Arabia | Q34: Asia
A35: 34 | B35: BHS | C35: BS | D35: BS | E35: Bahamas | F35: Bahamas (the); Bahamas, The | I35: 1 | J35: Bahamas | K35: Bahamas | L35: 8 | M35: Southern America | N35: Bahamas (the) | O35: 0 | P35: Central America and the Caribbean | Q35: North America
A36: 35 | B36: BIH | C36: BA | D36: BA | E36: Bosnia and Herzegovina | F36: Bosnia-Herzegovina; Bosnia and Herz.; Bosnia Herzegovina; Bosnia Herzegov.; Bosnia; Bosnia-Hercegovina | I36: 0 | J36: Bosnia and Herzegovina | M36: Europe | O36: 0 | P36: Europe | Q36: Europe
A37: 36 | B37: BLM | C37: BL | D37: BL | E37: Saint-Barthélemy | F37: St Barthélemy; St. Barthélemy; Saint-Barthélemy; Barthelemy; Saint Barthelemy; Saint Barthélemy | I37: 1 | J37: Saint-Barthélemy | K37: St. Martin-St. Barthelemy | L37: 8 | M37: Southern America | N37: Saint Barthelemy | O37: 0 | P37: Central America and the Caribbean | Q37: North America
A38: 37 | B38: BLR | C38: BY | D38: BY | E38: Belarus | F38: Western Palaearctic Region - Belarus | I38: 0 | J38: Belarus | K38: Belarus | L38: 1 | M38: Europe | N38: Belarus | O38: 0 | P38: Europe | Q38: Europe
A39: 38 | B39: BLZ | C39: BZ | D39: BZ | E39: Belize | I39: 0 | J39: Belize | K39: Belize | L39: 8 | M39: Southern America | N39: Belize | O39: 0 | P39: Central America and the Caribbean | Q39: North America
A40: 39 | B40: BMU | C40: BM | D40: BM | E40: Bermuda | F40: Bermuda (United Kingdom) | I40: 1 | J40: Bermuda | K40: Bermuda | L40: 8 | M40: Southern America | N40: Bermuda | O40: 0 | P40: Central America and the Caribbean | Q40: North America
A41: 40 | B41: BOL | C41: BO | D41: BO | E41: Bolivia | F41: Bolivia (Plurinational State of); Bolivia, Plurinational State of; Bolivia, Plurinational States of | I41: 0 | J41: Bolivia | L41: 8 | M41: Southern America | N41: Bolivia (Plurinational State of) | O41: 0 | P41: Southern America | Q41: South America
A42: 41 | B42: BRA | C42: BR | D42: BR | E42: Brazil | F42: Brazil North; Brazil Northeast; Brazil West-Central; Brazil Southeast; Brazil South; Southeastern Brazil; Neotropical Region - Brazil | I42: 0 | J42: Brazil | L42: 8 | M42: Southern America | N42: Brazil | O42: 0 | P42: Southern America | Q42: South America
A43: 42 | B43: BRB | C43: BB | D43: BB | E43: Barbados | I43: 1 | J43: Barbados | K43: Barbados | L43: 8 | M43: Southern America | N43: Barbados | O43: 0 | P43: Central America and the Caribbean | Q43: North America
A44: 43 | B44: BRN | C44: BN | D44: BN | E44: Brunei | F44: Brunei Darussalam; Brunei Darsm | I44: 0 | J44: Brunei | M44: Asia-Tropical | O44: 0 | P44: Southern Asia | Q44: Asia
A45: 44 | B45: BTN | C45: BT | D45: BT | E45: Bhutan | I45: 0 | J45: Bhutan | M45: Asia-Tropical | O45: 0 | P45: Southern Asia | Q45: Asia
A46: 45 | B46: BVT | C46: BV | D46: BV | E46: Bouvet Island | I46: 1 | J46: Bouvet Island | M46: Antarctic | O46: 0 | P46: Antarctic | Q46: Antarctica
A47: 46 | B47: BWA | C47: BW | D47: BW | E47: Botswana | I47: 0 | J47: Botswana | K47: Botswana | L47: 2 | M47: Africa | N47: Botswana | O47: 0 | P47: Sub-Saharan Africa | Q47: Africa
A48: 47 | B48: CAF | C48: CF | D48: CF | E48: Central African Republic | F48: Central African Rep.; Central African Repu; Central Afr. Rp | I48: 0 | J48: Central African Republic | K48: Central African Republic | L48: 2 | M48: Africa | N48: Central African Republic (the) | O48: 0 | P48: Sub-Saharan Africa | Q48: Africa
A49: 48 | B49: CAN | C49: CA | D49: CA | E49: Canada | F49: Western Canada; Eastern Canada; Upper Canada; Lower Canada; Nearctic Region - Eastern Canada; Nearctic Region - Western Canada | I49: 0 | J49: Canada | L49: 7 | M49: Northern America | N49: Canada | O49: 0 | P49: Northern America | Q49: North America
A50: 49 | B50: CCK | C50: CC | D50: CC | E50: Cocos Islands | F50: Keeling; Cocos (Keeling) Islands; Cocos Is. (Keel); Cocos (Keeling) Is.; Cocos-Keeling Island | I50: 1 | J50: Cocos Islands | L50: 4 | M50: Asia-Tropical | N50: Cocos (Keeling) Islands (the) | O50: 0 | P50: Southern Asia | Q50: Asia
A51: 50 | B51: CHE | C51: CH | D51: CH | E51: Switzerland | F51: Western Palaearctic Region - Switzerland; Schweiz | I51: 0 | J51: Switzerland | K51: Switzerland | L51: 1 | M51: Europe | N51: Switzerland | O51: 0 | P51: Europe | Q51: Europe
A52: 51 | B52: CHL | C52: CL | D52: CL | E52: Chile | F52: Chile North; Chile_n; Chile South; Chile_s; Chile Central; Chile_c; Chile_nc | I52: 0 | J52: Chile | L52: 8 | M52: Southern America | N52: Chile | O52: 0 | P52: Southern America | Q52: South America
A53: 52 | B53: CHN | C53: CN | D53: CN | E53: China | F53: China North-Central; China Southeast; China North-Central; China South-Central; Eastern Palaearctic Region - China; Eastern Palaearctic Region - China North-Central; Eastern Palaearctic Region - China South-Central; Oriental Region - China; Oriental Region - China South-Central; Oriental Region - China Southeast; Mainland, China; China(HL, JL, BJ, HA, HE, LN, SD, SN, SX, TJ, GS, NM, NX, XJ, QH, XZ); China(BJ, HA, HE, LN, SD, SN, SX, TJ); China(HL, JL, BJ, HA, HE, LN, SD, SN, SX, TJ); China(HL, JL, GS, NM, NX); China(HL, JL); China(HL, JL, BJ, HA, HE, LN, SD, SN, SX, TJ, GS, NM, NX); China(BJ, HA, HE, LN, SD, SN, SX, TJ, GS, NM, NX); China(BJ, HA, HE, LN, SD, SN, SX, TJ, XJ); China(HL, JL, BJ, HA, HE, LN, SD, SN, SX, TJ, XJ) | I53: 0 | J53: China | L53: 3 | M53: Asia-Temperate | N53: China | O53: 0 | P53: Eastern Asia | Q53: Asia
A54: 53 | B54: CIV | C54: CI | D54: CI | E54: Côte d'Ivoire | F54: Cote D'Ivoire; Cote d'Ivoire; Ivory Coast; Côte D'ivoire; C“te d'Ivoire; Cote d'Ivore; Cote dIvoire; C�te d'Ivoire | I54: 0 | J54: Côte d'Ivoire | K54: Cote d'Ivoire | L54: 2 | M54: Africa | N54: Côte d'Ivoire | O54: 0 | P54: Sub-Saharan Africa | Q54: Africa
A55: 54 | B55: CMR | C55: CM | D55: CM | E55: Cameroon | I55: 0 | J55: Cameroon | K55: Cameroon | L55: 2 | M55: Africa | N55: Cameroon | O55: 0 | P55: Sub-Saharan Africa | Q55: Africa
A56: 55 | B56: COD | C56: CD | D56: CD | E56: Democratic Republic of the Congo | F56: Congo, Democratic Republic of; Congo (the Democratic Republic of the); Congo, Democratic Republic of the; DR Congo; Democratic Republic of Congo; Congo, Dem. Rep.; Dem. Rep. Congo; Congo Dem Rp; Congo, the Democratic Republic of the; Congo, Republic of the; Congo Democratic Republic | I56: 0 | J56: Democratic Republic of the Congo | K56: Democratic Republic of the Congo | L56: 2 | M56: Africa | N56: Congo (the Democratic Republic of the) | O56: 0 | P56: Sub-Saharan Africa | Q56: Africa
A57: 56 | B57: COG | C57: CG | D57: CG | E57: Republic of the Congo | F57: Republic of Congo; Congo, Republic of; Congo, Rep.; Congo | I57: 0 | J57: Republic of Congo | K57: Congo | L57: 2 | M57: Africa | N57: Congo (the) | O57: 0 | P57: Sub-Saharan Africa | Q57: Africa
A58: 57 | B58: COK | C58: CK | D58: CK | E58: Cook Islands | F58: Cook Is.; Cook Isds; Cook Is. | I58: 1 | J58: Cook Islands | L58: 6 | M58: Pacific | N58: Cook Islands (the) | O58: 0 | P58: Pacific | Q58: Oceania
A59: 58 | B59: COL | C59: CO | D59: CO | E59: Colombia | F59: Neotropical Region - Colombia | I59: 0 | J59: Colombia | K59: Colombia | L59: 8 | M59: Southern America | N59: Colombia | O59: 0 | P59: Southern America | Q59: South America
A60: 59 | B60: COM | C60: KM | D60: KM | E60: Comoros | I60: 1 | J60: Comoros | K60: Comoros | L60: 2 | M60: Africa | N60: Comoros (the) | O60: 0 | P60: Sub-Saharan Africa | Q60: Africa
A61: 60 | B61: CPV | C61: CV | D61: CV | E61: Cape Verde | F61: Cabo Verde; Cape Verde Islands; Cape Verde archipelago | I61: 1 | J61: Cabo Verde | K61: Cape Verde | L61: 2 | M61: Africa | N61: Cabo Verde | O61: 0 | P61: Sub-Saharan Africa | Q61: Africa
A62: 61 | B62: CRI | C62: CR | D62: CR | E62: Costa Rica | F62: Cocos I. (C.R.); Cocos Island (Costa Rica); Neotropical Region - Costa Rica | I62: 0 | J62: Costa Rica | K62: Costa Rica | L62: 8 | M62: Southern America | N62: Costa Rica | O62: 0 | P62: Central America and the Caribbean | Q62: North America
A63: 62 | B63: CUB | C63: CU | D63: CU | E63: Cuba | F63: Neotropical Region - Cuba | I63: 1 | J63: Cuba | K63: Cuba | L63: 8 | M63: Southern America | N63: Cuba | O63: 0 | P63: Central America and the Caribbean | Q63: North America
A64: 63 | B64: CXR | C64: CX | D64: CX | E64: Christmas Island | F64: Christmas I.; Christmas Island (Indian Ocean) | I64: 1 | J64: Christmas Island | K64: Christmas Island | L64: 4 | M64: Asia-Tropical | N64: Christmas Island | O64: 0 | P64: Southern Asia | Q64: Asia
A65: 64 | B65: CYM | C65: KY | D65: KY | E65: Cayman Islands | F65: Cayman Islands; Cayman Islands (USA); Cayman Is.; Cayman Island | I65: 1 | J65: Cayman Islands | K65: Cayman Islands | L65: 8 | M65: Southern America | N65: Cayman Islands (the) | O65: 0 | P65: Central America and the Caribbean | Q65: North America
A66: 65 | B66: CYP | C66: CY | D66: CY | E66: Cyprus | I66: 1 | J66: Cyprus | K66: Cyprus | L66: 3 | M66: Asia-Temperate | N66: Cyprus | O66: 0 | P66: Western Asia | Q66: Asia
A67: 66 | B67: CZE | C67: CZ | D67: CZ | E67: Czech Republic | F67: Czechia; Czech Rep.; the Czech Republic; Czech Repoublic | I67: 0 | J67: Czechia | K67: Czech Republic | L67: 1 | M67: Europe | N67: Czech Republic (the) | O67: 0 | P67: Europe | Q67: Europe
A68: 67 | B68: DEU | C68: DE | D68: DE | E68: Germany | F68: Germany (mainland) | I68: 0 | J68: Germany | L68: 1 | M68: Europe | N68: Germany | O68: 0 | P68: Europe | Q68: Europe
A69: 68 | B69: DJI | C69: DJ | D69: DJ | E69: Djibouti | I69: 0 | J69: Djibouti | K69: Djibouti | L69: 2 | M69: Africa | N69: Djibouti | O69: 0 | P69: Sub-Saharan Africa | Q69: Africa
A70: 69 | B70: DMA | C70: DM | D70: DM | E70: Dominica | I70: 1 | J70: Dominica | K70: Dominica | L70: 8 | M70: Southern America | N70: Dominica | O70: 0 | P70: Central America and the Caribbean | Q70: North America
A71: 70 | B71: DNK | C71: DK | D71: DK | E71: Denmark | I71: 0 | J71: Denmark | K71: Denmark | L71: 1 | M71: Europe | N71: Denmark | O71: 0 | P71: Europe | Q71: Europe
A72: 71 | B72: DOM | C72: DO | D72: FR | E72: Dominican Republic | F72: Dominican Rep.; Dominican Rp; the Dominican Republic | I72: 1 | J72: Dominican Republic | K72: Dominican Republic | L72: 8 | M72: Southern America | N72: Dominican Republic (the) | O72: 0 | P72: Central America and the Caribbean | Q72: North America
A73: 72 | B73: DZA | C73: DZ | D73: DZ | E73: Algeria | I73: 0 | J73: Algeria | K73: Algeria | L73: 2 | M73: Africa | N73: Algeria | O73: 0 | P73: Saharo-Arabia | Q73: Africa
A74: 73 | B74: ECU | C74: EC | D74: EC | E74: Ecuador | I74: 0 | J74: Ecuador | L74: 8 | M74: Southern America | N74: Ecuador | O74: 0 | P74: Southern America | Q74: South America
A75: 74 | B75: ECU | C75: EC | D75: EC | E75: Galapagos | F75: Galápagos; Galapagos Islands; Española; Fernandina; Floreana; Genovesa; Isabela; Pinta; Pinzón; San Cristóbal; Santa Cruz (Galapagos); Santa Fé; Santiago; Ecuador (Galapagos); Galapagos Is.; GalÃ¡pagos; Galápagos; Santa Cruz Is.; Galapagos Islands | I75: 1 | J75: Ecuador | L75: 8 | M75: Southern America | N75: Ecuador | O75: 0 | P75: Southern America | Q75: South America
A76: 75 | B76: EGY | C76: EG | D76: EG | E76: Egypt | F76: Egypt, Arab Rep.; Western Palaearctic Region - Egypt | I76: 0 | J76: Egypt | K76: Egypt | L76: 2 | M76: Africa | N76: Egypt | O76: 0 | P76: Saharo-Arabia | Q76: Africa
A77: 76 | B77: ERI | C77: ER | D77: ER | E77: Eritrea | I77: 0 | J77: Eritrea | K77: Eritrea | L77: 2 | M77: Africa | N77: Eritrea | O77: 0 | P77: Sub-Saharan Africa | Q77: Africa
A78: 77 | B78: ESH | C78: EH | D78: EH | E78: Western Sahara | F78: Western Sahara*; West Sahara | I78: 0 | J78: Western Sahara | K78: Western Sahara | L78: 2 | M78: Africa | N78: Western Sahara | O78: 0 | P78: Saharo-Arabia | Q78: Africa
A79: 78 | B79: ESP | C79: ES | D79: ES | E79: Balearic Islands | F79: Islas Baleares; Balearen; Balear; Spain (Balearic islands); Baleares | I79: 1 | J79: Spain | K79: Balearic Islands | L79: 1 | M79: Europe | N79: Spain | O79: 0 | P79: Europe | Q79: Europe
A80: 79 | B80: ESP | C80: ES | D80: ES | E80: Canary Islands | F80: El Hierro; Fuerteventura; Gran Canaria; La Gomera; La Palma; Lanzarote; Tenerife; Spain (Canary islands); Canary Islands (Spain); Canary Island; Canarias; Islas Canarias; Canárias; Canary Is.; Canary Is | I80: 1 | J80: Spain | K80: Canary Islands | L80: 2 | M80: Africa | N80: Spain | O80: 0 | P80: Sub-Saharan Africa | Q80: Africa
A81: 80 | B81: ESP | C81: ES | D81: ES | E81: Spain | F81: Spain (mainland) | I81: 0 | J81: Spain | K81: Spain (mainland) | L81: 1 | M81: Europe | N81: Spain | O81: 0 | P81: Europe | Q81: Europe
A82: 81 | B82: EST | C82: EE | D82: EE | E82: Estonia | I82: 0 | J82: Estonia | K82: Estonia | L82: 1 | M82: Europe | N82: Estonia | O82: 0 | P82: Europe | Q82: Europe
A83: 82 | B83: ETH | C83: ET | D83: ET | E83: Ethiopia | F83: Western Palaearctic Region - Ethiopia | I83: 0 | J83: Ethiopia | K83: Ethiopia | L83: 2 | M83: Africa | N83: Ethiopia | O83: 0 | P83: Sub-Saharan Africa | Q83: Africa
A84: 83 | B84: FIN | C84: FI | D84: FI | E84: Finland | F84: Finland (mainland) | I84: 0 | J84: Finland | K84: Finland | L84: 1 | M84: Europe | N84: Finland | O84: 0 | P84: Europe | Q84: Europe
A85: 84 | B85: FJI | C85: FJ | D85: FJ | E85: Fiji | F85: Fiji Island | I85: 1 | J85: Fiji | L85: 6 | M85: Pacific | N85: Fiji | O85: 0 | P85: Pacific | Q85: Oceania
A86: 85 | B86: FLK | C86: FK | D86: FK | E86: Falkland Islands | F86: Malvinas; Falkland Islands (United Kingdom); Falkland Is.; Falkland Islands (Malvinas); Falkland; Falklands/Malvinas | I86: 1 | J86: Falkland Islands | M86: Antarctic | O86: 0 | P86: Antarctic | Q86: Antarctica
A87: 86 | B87: FRA | C87: FR | D87: SA | E87: France | F87: Western Palaearctic Region - France; France (mainland) | I87: 0 | J87: France | K87: France (mainland) | L87: 1 | M87: Europe | N87: France | O87: 0 | P87: Europe | Q87: Europe
A88: 87 | B88: FRO | C88: FO | D88: FO | E88: Faroe Islands | F88: Faroe; Faeroe Isds; Faeroe Is. | I88: 1 | J88: Faroe Islands | K88: Faroe Islands | L88: 1 | M88: Europe | N88: Faroe Islands (the) | O88: 0 | P88: Europe | Q88: Europe
A89: 88 | B89: FSM | C89: FM | D89: FM | E89: Micronesia | F89: Micronesia (Federated States of); Micronesia; Federated States of Micronesia; Chuuk; Pohnpei; Micronesia, Fed. Sts.; FS Micronesia; Micronesia (the Federated States of); MICRONESIA, FEDERATED STATES OF | I89: 1 | J89: Micronesia | L89: 6 | M89: Pacific | O89: 0 | P89: Pacific | Q89: Oceania
A90: 89 | B90: GAB | C90: GA | D90: GA | E90: Gabon | I90: 0 | J90: Gabon | K90: Gabon | L90: 2 | M90: Africa | N90: Gabon | O90: 0 | P90: Sub-Saharan Africa | Q90: Africa
A91: 90 | B91: GBR | C91: GB | D91: GB | E91: Shetland Islands | I91: 1 | J91: United Kingdom of Great Britain and Northern Ireland (the) | L91: 1 | M91: Europe | N91: United Kingdom of Great Britain and Northern Ireland (the) | O91: 0 | P91: Europe | Q91: Europe
A92: 91 | B92: GBR | C92: GB | D92: GB | E92: United Kingdom of Great Britain and Northern Ireland | F92: United Kingdom; UK; the United Kingdom; Western Palaearctic Region - United Kingdom; United Kingdom of Great Britain and Northern Ireland (the); United Kingdom of Great Britain and Northern Ireland; United Kingdom (Britain) | I92: 1 | J92: United Kingdom of Great Britain and Northern Ireland (the) | L92: 1 | M92: Europe | N92: United Kingdom of Great Britain and Northern Ireland (the) | O92: 0 | P92: Europe | Q92: Europe
A93: 92 | B93: GEO | C93: GE | D93: GE | E93: Georgia | F93: Georgia_Europe(country); Georgia (Republic of) | I93: 0 | J93: Georgia | K93: Georgia | L93: 3 | M93: Asia-Temperate | N93: Georgia | O93: 0 | P93: Western Asia | Q93: Asia
A94: 93 | B94: GGY | C94: GG | D94: GG | E94: Guernsey | I94: 1 | J94: Guernsey | M94: Europe | O94: 0 | P94: Europe | Q94: Europe
A95: 94 | B95: GHA | C95: GH | D95: GH | E95: Ghana | I95: 0 | J95: Ghana | K95: Ghana | L95: 2 | M95: Africa | N95: Ghana | O95: 0 | P95: Sub-Saharan Africa | Q95: Africa
A96: 95 | B96: GIB | C96: GI | D96: GI | E96: Gibraltar | I96: 0 | J96: Gibraltar | M96: Europe | O96: 0 | P96: Europe | Q96: Europe
A97: 96 | B97: GIN | C97: GN | D97: GN | E97: Guinea | I97: 0 | J97: Guinea | K97: Guinea | L97: 2 | M97: Africa | N97: Guinea | O97: 0 | P97: Sub-Saharan Africa | Q97: Africa
A98: 97 | B98: GLP | C98: GP | D98: GP | E98: Guadeloupe | F98: Guadalupe Island; Guadeloupe (France); Guadalupe I. | I98: 1 | J98: Guadeloupe | L98: 8 | M98: Southern America | N98: Guadeloupe | O98: 0 | P98: Central America and the Caribbean | Q98: North America
A99: 98 | B99: GMB | C99: GM | D99: GM | E99: Gambia | F99: Gambia, The | I99: 0 | J99: Gambia | K99: Gambia | L99: 2 | M99: Africa | N99: Gambia (the) | O99: 0 | P99: Sub-Saharan Africa | Q99: Africa
A100: 99 | B100: GNB | C100: GW | D100: GW | E100: Guinea-Bissau | F100: Guinea Bissau | I100: 0 | J100: Guinea-Bissau | L100: 2 | M100: Africa | N100: Guinea-Bissau | O100: 0 | P100: Sub-Saharan Africa | Q100: Africa
...

Sheet stateProvince
A1: locationID | B1: ISO3 | C1: ISO_1 | D1: country_code | E1: location | F1: location_var | G1: gadm1_name | H1: gadm1_var | I1: island | J1: gadm0_name | K1: tdwg4_name | L1: tdwg1 | M1: tdwg1_name | N1: glonaf_country | O1: adm_level | P1: sinas_region | Q1: continent
A2: 277 | B2: AFG | D2: AF | E2: Afghanistan | F2: =IFERROR(IF(VLOOKUP(E2, location!E$2:F$290, 2, FALSE) = 0, "", VLOOKUP(E2, location!E$2:F$290, 2, FALSE)), "") | G2: Badakhshan | H2: Badahšan | I2: 0 | J2: Afghanistan | K2: Afghanistan | L2: 3 | M2: Asia-Temperate | N2: Afghanistan | O2: 1 | P2: =IFERROR(VLOOKUP(E2, location!$E$2:$P$290, 12, FALSE), "") -> Western Asia | Q2: Asia
A3: 278 | B3: AFG | C3: AF-BDG | D3: AF | E3: Afghanistan | F3: =IFERROR(IF(VLOOKUP(E3, location!E$2:F$290, 2, FALSE) = 0, "", VLOOKUP(E3, location!E$2:F$290, 2, FALSE)), "") | G3: Badghis | H3: Badghes; Badghisat; Badgis | I3: 0 | J3: Afghanistan | K3: Afghanistan | L3: 3 | M3: Asia-Temperate | N3: Afghanistan | O3: 1 | P3: =IFERROR(VLOOKUP(E3, location!$E$2:$P$290, 12, FALSE), "") -> Western Asia | Q3: Asia
A4: 279 | B4: AFG | C4: AF-BGL | D4: AF | E4: Afghanistan | F4: =IFERROR(IF(VLOOKUP(E4, location!E$2:F$290, 2, FALSE) = 0, "", VLOOKUP(E4, location!E$2:F$290, 2, FALSE)), "") | G4: Baghlan | H4: Baglan; Bughlan | I4: 0 | J4: Afghanistan | K4: Afghanistan | L4: 3 | M4: Asia-Temperate | N4: Afghanistan | O4: 1 | P4: =IFERROR(VLOOKUP(E4, location!$E$2:$P$290, 12, FALSE), "") -> Western Asia | Q4: Asia
A5: 280 | B5: AFG | C5: AF-BAL | D5: AF | E5: Afghanistan | F5: =IFERROR(IF(VLOOKUP(E5, location!E$2:F$290, 2, FALSE) = 0, "", VLOOKUP(E5, location!E$2:F$290, 2, FALSE)), "") | G5: Balkh | H5: Balh; Mazar-i-Sharif; Mazar | I5: 0 | J5: Afghanistan | K5: Afghanistan | L5: 3 | M5: Asia-Temperate | N5: Afghanistan | O5: 1 | P5: =IFERROR(VLOOKUP(E5, location!$E$2:$P$290, 12, FALSE), "") -> Western Asia | Q5: Asia
A6: 281 | B6: AFG | C6: AF-BAM | D6: AF | E6: Afghanistan | F6: =IFERROR(IF(VLOOKUP(E6, location!E$2:F$290, 2, FALSE) = 0, "", VLOOKUP(E6, location!E$2:F$290, 2, FALSE)), "") | G6: Bamyan | I6: 0 | J6: Afghanistan | K6: Afghanistan | L6: 3 | M6: Asia-Temperate | N6: Afghanistan | O6: 1 | P6: =IFERROR(VLOOKUP(E6, location!$E$2:$P$290, 12, FALSE), "") -> Western Asia | Q6: Asia
A7: 282 | B7: AFG | C7: AF-DAY | D7: AF | E7: Afghanistan | F7: =IFERROR(IF(VLOOKUP(E7, location!E$2:F$290, 2, FALSE) = 0, "", VLOOKUP(E7, location!E$2:F$290, 2, FALSE)), "") | G7: Daykundi | I7: 0 | J7: Afghanistan | K7: Afghanistan | L7: 3 | M7: Asia-Temperate | N7: Afghanistan | O7: 1 | P7: =IFERROR(VLOOKUP(E7, location!$E$2:$P$290, 12, FALSE), "") -> Western Asia | Q7: Asia
A8: 283 | B8: AFG | C8: AF-FRA | D8: AF | E8: Afghanistan | F8: =IFERROR(IF(VLOOKUP(E8, location!E$2:F$290, 2, FALSE) = 0, "", VLOOKUP(E8, location!E$2:F$290, 2, FALSE)), "") | G8: Farah | I8: 0 | J8: Afghanistan | K8: Afghanistan | L8: 3 | M8: Asia-Temperate | N8: Afghanistan | O8: 1 | P8: =IFERROR(VLOOKUP(E8, location!$E$2:$P$290, 12, FALSE), "") -> Western Asia | Q8: Asia
A9: 284 | B9: AFG | C9: AF-FYB | D9: AF | E9: Afghanistan | F9: =IFERROR(IF(VLOOKUP(E9, location!E$2:F$290, 2, FALSE) = 0, "", VLOOKUP(E9, location!E$2:F$290, 2, FALSE)), "") | G9: Faryab | H9: Fariab; Maimana; Meymaneh | I9: 0 | J9: Afghanistan | K9: Afghanistan | L9: 3 | M9: Asia-Temperate | N9: Afghanistan | O9: 1 | P9: =IFERROR(VLOOKUP(E9, location!$E$2:$P$290, 12, FALSE), "") -> Western Asia | Q9: Asia
A10: 285 | B10: AFG | C10: AF-GHA | D10: AF | E10: Afghanistan | F10: =IFERROR(IF(VLOOKUP(E10, location!E$2:F$290, 2, FALSE) = 0, "", VLOOKUP(E10, location!E$2:F$290, 2, FALSE)), "") | G10: Ghazni | H10: Gazni | I10: 0 | J10: Afghanistan | K10: Afghanistan | L10: 3 | M10: Asia-Temperate | N10: Afghanistan | O10: 1 | P10: =IFERROR(VLOOKUP(E10, location!$E$2:$P$290, 12, FALSE), "") -> Western Asia | Q10: Asia
A11: 286 | B11: AFG | C11: AF-GHO | D11: AF | E11: Afghanistan | F11: =IFERROR(IF(VLOOKUP(E11, location!E$2:F$290, 2, FALSE) = 0, "", VLOOKUP(E11, location!E$2:F$290, 2, FALSE)), "") | G11: Ghor | H11: Gawr; Ghore; Ghour; Ghur | I11: 0 | J11: Afghanistan | K11: Afghanistan | L11: 3 | M11: Asia-Temperate | N11: Afghanistan | O11: 1 | P11: =IFERROR(VLOOKUP(E11, location!$E$2:$P$290, 12, FALSE), "") -> Western Asia | Q11: Asia
A12: 287 | B12: AFG | D12: AF | E12: Afghanistan | F12: =IFERROR(IF(VLOOKUP(E12, location!E$2:F$290, 2, FALSE) = 0, "", VLOOKUP(E12, location!E$2:F$290, 2, FALSE)), "") | G12: Hilmand | H12: Girishk; Hilmend | I12: 0 | J12: Afghanistan | K12: Afghanistan | L12: 3 | M12: Asia-Temperate | N12: Afghanistan | O12: 1 | P12: =IFERROR(VLOOKUP(E12, location!$E$2:$P$290, 12, FALSE), "") -> Western Asia | Q12: Asia
A13: 288 | B13: AFG | D13: AF | E13: Afghanistan | F13: =IFERROR(IF(VLOOKUP(E13, location!E$2:F$290, 2, FALSE) = 0, "", VLOOKUP(E13, location!E$2:F$290, 2, FALSE)), "") | G13: Hirat | I13: 0 | J13: Afghanistan | K13: Afghanistan | L13: 3 | M13: Asia-Temperate | N13: Afghanistan | O13: 1 | P13: =IFERROR(VLOOKUP(E13, location!$E$2:$P$290, 12, FALSE), "") -> Western Asia | Q13: Asia
A14: 289 | B14: AFG | D14: AF | E14: Afghanistan | F14: =IFERROR(IF(VLOOKUP(E14, location!E$2:F$290, 2, FALSE) = 0, "", VLOOKUP(E14, location!E$2:F$290, 2, FALSE)), "") | G14: Jawzjan | H14: Jaozjan; Jozjan; Juzjan; Jouzjan; Sh | I14: 0 | J14: Afghanistan | K14: Afghanistan | L14: 3 | M14: Asia-Temperate | N14: Afghanistan | O14: 1 | P14: =IFERROR(VLOOKUP(E14, location!$E$2:$P$290, 12, FALSE), "") -> Western Asia | Q14: Asia
A15: 290 | B15: AFG | C15: AF-KAB | D15: AF | E15: Afghanistan | F15: =IFERROR(IF(VLOOKUP(E15, location!E$2:F$290, 2, FALSE) = 0, "", VLOOKUP(E15, location!E$2:F$290, 2, FALSE)), "") | G15: Kabul | H15: Cabul; Kabol; Kaboul | I15: 0 | J15: Afghanistan | K15: Afghanistan | L15: 3 | M15: Asia-Temperate | N15: Afghanistan | O15: 1 | P15: =IFERROR(VLOOKUP(E15, location!$E$2:$P$290, 12, FALSE), "") -> Western Asia | Q15: Asia
A16: 291 | B16: AFG | C16: AF-KAN | D16: AF | E16: Afghanistan | F16: =IFERROR(IF(VLOOKUP(E16, location!E$2:F$290, 2, FALSE) = 0, "", VLOOKUP(E16, location!E$2:F$290, 2, FALSE)), "") | G16: Kandahar | H16: Qandahar | I16: 0 | J16: Afghanistan | K16: Afghanistan | L16: 3 | M16: Asia-Temperate | N16: Afghanistan | O16: 1 | P16: =IFERROR(VLOOKUP(E16, location!$E$2:$P$290, 12, FALSE), "") -> Western Asia | Q16: Asia
A17: 292 | B17: AFG | D17: AF | E17: Afghanistan | F17: =IFERROR(IF(VLOOKUP(E17, location!E$2:F$290, 2, FALSE) = 0, "", VLOOKUP(E17, location!E$2:F$290, 2, FALSE)), "") | G17: Kapisa | H17: Kapesa | I17: 0 | J17: Afghanistan | K17: Afghanistan | L17: 3 | M17: Asia-Temperate | N17: Afghanistan | O17: 1 | P17: =IFERROR(VLOOKUP(E17, location!$E$2:$P$290, 12, FALSE), "") -> Western Asia | Q17: Asia
A18: 293 | B18: AFG | C18: AF-KHO | D18: AF | E18: Afghanistan | F18: =IFERROR(IF(VLOOKUP(E18, location!E$2:F$290, 2, FALSE) = 0, "", VLOOKUP(E18, location!E$2:F$290, 2, FALSE)), "") | G18: Khost | I18: 0 | J18: Afghanistan | K18: Afghanistan | L18: 3 | M18: Asia-Temperate | N18: Afghanistan | O18: 1 | P18: =IFERROR(VLOOKUP(E18, location!$E$2:$P$290, 12, FALSE), "") -> Western Asia | Q18: Asia
A19: 294 | B19: AFG | C19: AF-KNR | D19: AF | E19: Afghanistan | F19: =IFERROR(IF(VLOOKUP(E19, location!E$2:F$290, 2, FALSE) = 0, "", VLOOKUP(E19, location!E$2:F$290, 2, FALSE)), "") | G19: Kunar | H19: Konarha; Kunarha | I19: 0 | J19: Afghanistan | K19: Afghanistan | L19: 3 | M19: Asia-Temperate | N19: Afghanistan | O19: 1 | P19: =IFERROR(VLOOKUP(E19, location!$E$2:$P$290, 12, FALSE), "") -> Western Asia | Q19: Asia
A20: 295 | B20: AFG | C20: AF-KDZ | D20: AF | E20: Afghanistan | F20: =IFERROR(IF(VLOOKUP(E20, location!E$2:F$290, 2, FALSE) = 0, "", VLOOKUP(E20, location!E$2:F$290, 2, FALSE)), "") | G20: Kunduz | H20: Kondoz; Qonduz; Qunduz | I20: 0 | J20: Afghanistan | K20: Afghanistan | L20: 3 | M20: Asia-Temperate | N20: Afghanistan | O20: 1 | P20: =IFERROR(VLOOKUP(E20, location!$E$2:$P$290, 12, FALSE), "") -> Western Asia | Q20: Asia
A21: 296 | B21: AFG | C21: AF-LAG | D21: AF | E21: Afghanistan | F21: =IFERROR(IF(VLOOKUP(E21, location!E$2:F$290, 2, FALSE) = 0, "", VLOOKUP(E21, location!E$2:F$290, 2, FALSE)), "") | G21: Laghman | H21: Lagman | I21: 0 | J21: Afghanistan | K21: Afghanistan | L21: 3 | M21: Asia-Temperate | N21: Afghanistan | O21: 1 | P21: =IFERROR(VLOOKUP(E21, location!$E$2:$P$290, 12, FALSE), "") -> Western Asia | Q21: Asia
A22: 297 | B22: AFG | C22: AF-LOG | D22: AF | E22: Afghanistan | F22: =IFERROR(IF(VLOOKUP(E22, location!E$2:F$290, 2, FALSE) = 0, "", VLOOKUP(E22, location!E$2:F$290, 2, FALSE)), "") | G22: Logar | H22: Lawghar; Loghar | I22: 0 | J22: Afghanistan | K22: Afghanistan | L22: 3 | M22: Asia-Temperate | N22: Afghanistan | O22: 1 | P22: =IFERROR(VLOOKUP(E22, location!$E$2:$P$290, 12, FALSE), "") -> Western Asia | Q22: Asia
A23: 298 | B23: AFG | C23: AF-NAN | D23: AF | E23: Afghanistan | F23: =IFERROR(IF(VLOOKUP(E23, location!E$2:F$290, 2, FALSE) = 0, "", VLOOKUP(E23, location!E$2:F$290, 2, FALSE)), "") | G23: Nangarhar | H23: Ningrahar; Eastern Province (Afghanistan) | I23: 0 | J23: Afghanistan | K23: Afghanistan | L23: 3 | M23: Asia-Temperate | N23: Afghanistan | O23: 1 | P23: =IFERROR(VLOOKUP(E23, location!$E$2:$P$290, 12, FALSE), "") -> Western Asia | Q23: Asia
A24: 299 | B24: AFG | C24: AF-NIM | D24: AF | E24: Afghanistan | F24: =IFERROR(IF(VLOOKUP(E24, location!E$2:F$290, 2, FALSE) = 0, "", VLOOKUP(E24, location!E$2:F$290, 2, FALSE)), "") | G24: Nimroz | H24: Neemroze; Nimrod; Nimrooz; Nimroze; | I24: 0 | J24: Afghanistan | K24: Afghanistan | L24: 3 | M24: Asia-Temperate | N24: Afghanistan | O24: 1 | P24: =IFERROR(VLOOKUP(E24, location!$E$2:$P$290, 12, FALSE), "") -> Western Asia | Q24: Asia
A25: 300 | B25: AFG | D25: AF | E25: Afghanistan | F25: =IFERROR(IF(VLOOKUP(E25, location!E$2:F$290, 2, FALSE) = 0, "", VLOOKUP(E25, location!E$2:F$290, 2, FALSE)), "") | G25: Nuristan | H25: Nooristan; Nuristão | I25: 0 | J25: Afghanistan | K25: Afghanistan | L25: 3 | M25: Asia-Temperate | N25: Afghanistan | O25: 1 | P25: =IFERROR(VLOOKUP(E25, location!$E$2:$P$290, 12, FALSE), "") -> Western Asia | Q25: Asia
A26: 301 | B26: AFG | D26: AF | E26: Afghanistan | F26: =IFERROR(IF(VLOOKUP(E26, location!E$2:F$290, 2, FALSE) = 0, "", VLOOKUP(E26, location!E$2:F$290, 2, FALSE)), "") | G26: Paktika | H26: Paktiya; Paktya; Southern Province | I26: 0 | J26: Afghanistan | K26: Afghanistan | L26: 3 | M26: Asia-Temperate | N26: Afghanistan | O26: 1 | P26: =IFERROR(VLOOKUP(E26, location!$E$2:$P$290, 12, FALSE), "") -> Western Asia | Q26: Asia
A27: 302 | B27: AFG | D27: AF | E27: Afghanistan | F27: =IFERROR(IF(VLOOKUP(E27, location!E$2:F$290, 2, FALSE) = 0, "", VLOOKUP(E27, location!E$2:F$290, 2, FALSE)), "") | G27: Paktya | H27: Paktiya; Southern Province | I27: 0 | J27: Afghanistan | K27: Afghanistan | L27: 3 | M27: Asia-Temperate | N27: Afghanistan | O27: 1 | P27: =IFERROR(VLOOKUP(E27, location!$E$2:$P$290, 12, FALSE), "") -> Western Asia | Q27: Asia
A28: 303 | B28: AFG | D28: AF | E28: Afghanistan | F28: =IFERROR(IF(VLOOKUP(E28, location!E$2:F$290, 2, FALSE) = 0, "", VLOOKUP(E28, location!E$2:F$290, 2, FALSE)), "") | G28: Panjshir | I28: 0 | J28: Afghanistan | K28: Afghanistan | L28: 3 | M28: Asia-Temperate | N28: Afghanistan | O28: 1 | P28: =IFERROR(VLOOKUP(E28, location!$E$2:$P$290, 12, FALSE), "") -> Western Asia | Q28: Asia
A29: 304 | B29: AFG | C29: AF-PAR | D29: AF | E29: Afghanistan | F29: =IFERROR(IF(VLOOKUP(E29, location!E$2:F$290, 2, FALSE) = 0, "", VLOOKUP(E29, location!E$2:F$290, 2, FALSE)), "") | G29: Parwan | H29: Charikar | I29: 0 | J29: Afghanistan | K29: Afghanistan | L29: 3 | M29: Asia-Temperate | N29: Afghanistan | O29: 1 | P29: =IFERROR(VLOOKUP(E29, location!$E$2:$P$290, 12, FALSE), "") -> Western Asia | Q29: Asia
A30: 305 | B30: AFG | C30: AF-SAM | D30: AF | E30: Afghanistan | F30: =IFERROR(IF(VLOOKUP(E30, location!E$2:F$290, 2, FALSE) = 0, "", VLOOKUP(E30, location!E$2:F$290, 2, FALSE)), "") | G30: Samangan | I30: 0 | J30: Afghanistan | K30: Afghanistan | L30: 3 | M30: Asia-Temperate | N30: Afghanistan | O30: 1 | P30: =IFERROR(VLOOKUP(E30, location!$E$2:$P$290, 12, FALSE), "") -> Western Asia | Q30: Asia
A31: 306 | B31: AFG | D31: AF | E31: Afghanistan | F31: =IFERROR(IF(VLOOKUP(E31, location!E$2:F$290, 2, FALSE) = 0, "", VLOOKUP(E31, location!E$2:F$290, 2, FALSE)), "") | G31: Sari Pul | H31: Sar-e Pul; Saripol | I31: 0 | J31: Afghanistan | K31: Afghanistan | L31: 3 | M31: Asia-Temperate | N31: Afghanistan | O31: 1 | P31: =IFERROR(VLOOKUP(E31, location!$E$2:$P$290, 12, FALSE), "") -> Western Asia | Q31: Asia
A32: 307 | B32: AFG | C32: AF-TAK | D32: AF | E32: Afghanistan | F32: =IFERROR(IF(VLOOKUP(E32, location!E$2:F$290, 2, FALSE) = 0, "", VLOOKUP(E32, location!E$2:F$290, 2, FALSE)), "") | G32: Takhar | H32: Takar | I32: 0 | J32: Afghanistan | K32: Afghanistan | L32: 3 | M32: Asia-Temperate | N32: Afghanistan | O32: 1 | P32: =IFERROR(VLOOKUP(E32, location!$E$2:$P$290, 12, FALSE), "") -> Western Asia | Q32: Asia
A33: 308 | B33: AFG | C33: AF-URU | D33: AF | E33: Afghanistan | F33: =IFERROR(IF(VLOOKUP(E33, location!E$2:F$290, 2, FALSE) = 0, "", VLOOKUP(E33, location!E$2:F$290, 2, FALSE)), "") | G33: Uruzgan | H33: Urozgan | I33: 0 | J33: Afghanistan | K33: Afghanistan | L33: 3 | M33: Asia-Temperate | N33: Afghanistan | O33: 1 | P33: =IFERROR(VLOOKUP(E33, location!$E$2:$P$290, 12, FALSE), "") -> Western Asia | Q33: Asia
A34: 309 | B34: AFG | D34: AF | E34: Afghanistan | F34: =IFERROR(IF(VLOOKUP(E34, location!E$2:F$290, 2, FALSE) = 0, "", VLOOKUP(E34, location!E$2:F$290, 2, FALSE)), "") | G34: Wardak | H34: Verdak; Wardag; Maiden | I34: 0 | J34: Afghanistan | K34: Afghanistan | L34: 3 | M34: Asia-Temperate | N34: Afghanistan | O34: 1 | P34: =IFERROR(VLOOKUP(E34, location!$E$2:$P$290, 12, FALSE), "") -> Western Asia | Q34: Asia
A35: 310 | B35: AFG | D35: AF | E35: Afghanistan | F35: =IFERROR(IF(VLOOKUP(E35, location!E$2:F$290, 2, FALSE) = 0, "", VLOOKUP(E35, location!E$2:F$290, 2, FALSE)), "") | G35: Zabul | H35: Zubul; Zaboul | I35: 0 | J35: Afghanistan | K35: Afghanistan | L35: 3 | M35: Asia-Temperate | N35: Afghanistan | O35: 1 | P35: =IFERROR(VLOOKUP(E35, location!$E$2:$P$290, 12, FALSE), "") -> Western Asia | Q35: Asia
A36: 311 | B36: AGO | C36: AO-BGO | D36: AO | E36: Angola | F36: =IFERROR(IF(VLOOKUP(E36, location!E$2:F$290, 2, FALSE) = 0, "", VLOOKUP(E36, location!E$2:F$290, 2, FALSE)), "") | G36: Bengo | I36: 0 | J36: Angola | K36: Angola | L36: 2 | M36: Africa | N36: Angola | O36: 1 | P36: =IFERROR(VLOOKUP(E36, location!$E$2:$P$290, 12, FALSE), "") -> Sub-Saharan Africa | Q36: Africa
A37: 312 | B37: AGO | C37: AO-BGU | D37: AO | E37: Angola | F37: =IFERROR(IF(VLOOKUP(E37, location!E$2:F$290, 2, FALSE) = 0, "", VLOOKUP(E37, location!E$2:F$290, 2, FALSE)), "") | G37: Benguela | H37: Benguella | I37: 0 | J37: Angola | K37: Angola | L37: 2 | M37: Africa | N37: Angola | O37: 1 | P37: =IFERROR(VLOOKUP(E37, location!$E$2:$P$290, 12, FALSE), "") -> Sub-Saharan Africa | Q37: Africa
A38: 313 | B38: AGO | D38: AO | E38: Angola | F38: =IFERROR(IF(VLOOKUP(E38, location!E$2:F$290, 2, FALSE) = 0, "", VLOOKUP(E38, location!E$2:F$290, 2, FALSE)), "") | G38: Bié | I38: 0 | J38: Angola | K38: Angola | L38: 2 | M38: Africa | N38: Angola | O38: 1 | P38: =IFERROR(VLOOKUP(E38, location!$E$2:$P$290, 12, FALSE), "") -> Sub-Saharan Africa | Q38: Africa
A39: 314 | B39: AGO | C39: AO-CAB | D39: AO | E39: Angola | F39: =IFERROR(IF(VLOOKUP(E39, location!E$2:F$290, 2, FALSE) = 0, "", VLOOKUP(E39, location!E$2:F$290, 2, FALSE)), "") | G39: Cabinda | I39: 0 | J39: Angola | K39: Angola | L39: 2 | M39: Africa | N39: Angola | O39: 1 | P39: =IFERROR(VLOOKUP(E39, location!$E$2:$P$290, 12, FALSE), "") -> Sub-Saharan Africa | Q39: Africa
A40: 315 | B40: AGO | C40: AO-CCU | D40: AO | E40: Angola | F40: =IFERROR(IF(VLOOKUP(E40, location!E$2:F$290, 2, FALSE) = 0, "", VLOOKUP(E40, location!E$2:F$290, 2, FALSE)), "") | G40: Cuando Cubango | I40: 0 | J40: Angola | K40: Angola | L40: 2 | M40: Africa | N40: Angola | O40: 1 | P40: =IFERROR(VLOOKUP(E40, location!$E$2:$P$290, 12, FALSE), "") -> Sub-Saharan Africa | Q40: Africa
A41: 316 | B41: AGO | D41: AO | E41: Angola | F41: =IFERROR(IF(VLOOKUP(E41, location!E$2:F$290, 2, FALSE) = 0, "", VLOOKUP(E41, location!E$2:F$290, 2, FALSE)), "") | G41: Cuanza Norte | H41: Cuanza-Nord; Kwanza Norte | I41: 0 | J41: Angola | K41: Angola | L41: 2 | M41: Africa | N41: Angola | O41: 1 | P41: =IFERROR(VLOOKUP(E41, location!$E$2:$P$290, 12, FALSE), "") -> Sub-Saharan Africa | Q41: Africa
A42: 317 | B42: AGO | D42: AO | E42: Angola | F42: =IFERROR(IF(VLOOKUP(E42, location!E$2:F$290, 2, FALSE) = 0, "", VLOOKUP(E42, location!E$2:F$290, 2, FALSE)), "") | G42: Cuanza Sul | H42: Cuanza-Sud; Kwanza Sul | I42: 0 | J42: Angola | K42: Angola | L42: 2 | M42: Africa | N42: Angola | O42: 1 | P42: =IFERROR(VLOOKUP(E42, location!$E$2:$P$290, 12, FALSE), "") -> Sub-Saharan Africa | Q42: Africa
A43: 318 | B43: AGO | C43: AO-CNN | D43: AO | E43: Angola | F43: =IFERROR(IF(VLOOKUP(E43, location!E$2:F$290, 2, FALSE) = 0, "", VLOOKUP(E43, location!E$2:F$290, 2, FALSE)), "") | G43: Cunene | I43: 0 | J43: Angola | K43: Angola | L43: 2 | M43: Africa | N43: Angola | O43: 1 | P43: =IFERROR(VLOOKUP(E43, location!$E$2:$P$290, 12, FALSE), "") -> Sub-Saharan Africa | Q43: Africa
A44: 319 | B44: AGO | C44: AO-HUA | D44: AO | E44: Angola | F44: =IFERROR(IF(VLOOKUP(E44, location!E$2:F$290, 2, FALSE) = 0, "", VLOOKUP(E44, location!E$2:F$290, 2, FALSE)), "") | G44: Huambo | I44: 0 | J44: Angola | K44: Angola | L44: 2 | M44: Africa | N44: Angola | O44: 1 | P44: =IFERROR(VLOOKUP(E44, location!$E$2:$P$290, 12, FALSE), "") -> Sub-Saharan Africa | Q44: Africa
A45: 320 | B45: AGO | D45: AO | E45: Angola | F45: =IFERROR(IF(VLOOKUP(E45, location!E$2:F$290, 2, FALSE) = 0, "", VLOOKUP(E45, location!E$2:F$290, 2, FALSE)), "") | G45: Huíla | I45: 0 | J45: Angola | K45: Angola | L45: 2 | M45: Africa | N45: Angola | O45: 1 | P45: =IFERROR(VLOOKUP(E45, location!$E$2:$P$290, 12, FALSE), "") -> Sub-Saharan Africa | Q45: Africa
A46: 321 | B46: AGO | C46: AO-LUA | D46: AO | E46: Angola | F46: =IFERROR(IF(VLOOKUP(E46, location!E$2:F$290, 2, FALSE) = 0, "", VLOOKUP(E46, location!E$2:F$290, 2, FALSE)), "") | G46: Luanda | H46: Loanda | I46: 0 | J46: Angola | K46: Angola | L46: 2 | M46: Africa | N46: Angola | O46: 1 | P46: =IFERROR(VLOOKUP(E46, location!$E$2:$P$290, 12, FALSE), "") -> Sub-Saharan Africa | Q46: Africa
A47: 322 | B47: AGO | D47: AO | E47: Angola | F47: =IFERROR(IF(VLOOKUP(E47, location!E$2:F$290, 2, FALSE) = 0, "", VLOOKUP(E47, location!E$2:F$290, 2, FALSE)), "") | G47: Lunda Norte | I47: 0 | J47: Angola | K47: Angola | L47: 2 | M47: Africa | N47: Angola | O47: 1 | P47: =IFERROR(VLOOKUP(E47, location!$E$2:$P$290, 12, FALSE), "") -> Sub-Saharan Africa | Q47: Africa
A48: 323 | B48: AGO | D48: AO | E48: Angola | F48: =IFERROR(IF(VLOOKUP(E48, location!E$2:F$290, 2, FALSE) = 0, "", VLOOKUP(E48, location!E$2:F$290, 2, FALSE)), "") | G48: Lunda Sul | I48: 0 | J48: Angola | K48: Angola | L48: 2 | M48: Africa | N48: Angola | O48: 1 | P48: =IFERROR(VLOOKUP(E48, location!$E$2:$P$290, 12, FALSE), "") -> Sub-Saharan Africa | Q48: Africa
A49: 324 | B49: AGO | D49: AO | E49: Angola | F49: =IFERROR(IF(VLOOKUP(E49, location!E$2:F$290, 2, FALSE) = 0, "", VLOOKUP(E49, location!E$2:F$290, 2, FALSE)), "") | G49: Malanje | H49: Malange | I49: 0 | J49: Angola | K49: Angola | L49: 2 | M49: Africa | N49: Angola | O49: 1 | P49: =IFERROR(VLOOKUP(E49, location!$E$2:$P$290, 12, FALSE), "") -> Sub-Saharan Africa | Q49: Africa
A50: 325 | B50: AGO | C50: AO-MOX | D50: AO | E50: Angola | F50: =IFERROR(IF(VLOOKUP(E50, location!E$2:F$290, 2, FALSE) = 0, "", VLOOKUP(E50, location!E$2:F$290, 2, FALSE)), "") | G50: Moxico | I50: 0 | J50: Angola | K50: Angola | L50: 2 | M50: Africa | N50: Angola | O50: 1 | P50: =IFERROR(VLOOKUP(E50, location!$E$2:$P$290, 12, FALSE), "") -> Sub-Saharan Africa | Q50: Africa
A51: 326 | B51: AGO | C51: AO-NAM | D51: AO | E51: Angola | F51: =IFERROR(IF(VLOOKUP(E51, location!E$2:F$290, 2, FALSE) = 0, "", VLOOKUP(E51, location!E$2:F$290, 2, FALSE)), "") | G51: Namibe | H51: Moçâmedes; Mossamedes | I51: 0 | J51: Angola | K51: Angola | L51: 2 | M51: Africa | N51: Angola | O51: 1 | P51: =IFERROR(VLOOKUP(E51, location!$E$2:$P$290, 12, FALSE), "") -> Sub-Saharan Africa | Q51: Africa
A52: 327 | B52: AGO | D52: AO | E52: Angola | F52: =IFERROR(IF(VLOOKUP(E52, location!E$2:F$290, 2, FALSE) = 0, "", VLOOKUP(E52, location!E$2:F$290, 2, FALSE)), "") | G52: Uíge | I52: 0 | J52: Angola | K52: Angola | L52: 2 | M52: Africa | N52: Angola | O52: 1 | P52: =IFERROR(VLOOKUP(E52, location!$E$2:$P$290, 12, FALSE), "") -> Sub-Saharan Africa | Q52: Africa
A53: 328 | B53: AGO | C53: AO-ZAI | D53: AO | E53: Angola | F53: =IFERROR(IF(VLOOKUP(E53, location!E$2:F$290, 2, FALSE) = 0, "", VLOOKUP(E53, location!E$2:F$290, 2, FALSE)), "") | G53: Zaire | I53: 0 | J53: Angola | K53: Angola | L53: 2 | M53: Africa | N53: Angola | O53: 1 | P53: =IFERROR(VLOOKUP(E53, location!$E$2:$P$290, 12, FALSE), "") -> Sub-Saharan Africa | Q53: Africa
A54: 329 | B54: AIA | D54: AI | E54: Anguilla | F54: =IFERROR(IF(VLOOKUP(E54, location!E$2:F$290, 2, FALSE) = 0, "", VLOOKUP(E54, location!E$2:F$290, 2, FALSE)), "") -> Anguilla Island | G54: Blowing Point | I54: 1 | J54: Anguilla | K54: Anguilla | L54: 8 | M54: Southern America | N54: Anguilla | O54: 1 | P54: =IFERROR(VLOOKUP(E54, location!$E$2:$P$290, 12, FALSE), "") -> Central America and the Caribbean | Q54: North America
A55: 330 | B55: AIA | D55: AI | E55: Anguilla | F55: =IFERROR(IF(VLOOKUP(E55, location!E$2:F$290, 2, FALSE) = 0, "", VLOOKUP(E55, location!E$2:F$290, 2, FALSE)), "") -> Anguilla Island | G55: Dog Island | I55: 1 | J55: Anguilla | K55: Anguilla | L55: 8 | M55: Southern America | N55: Anguilla | O55: 1 | P55: =IFERROR(VLOOKUP(E55, location!$E$2:$P$290, 12, FALSE), "") -> Central America and the Caribbean | Q55: North America
A56: 331 | B56: AIA | D56: AI | E56: Anguilla | F56: =IFERROR(IF(VLOOKUP(E56, location!E$2:F$290, 2, FALSE) = 0, "", VLOOKUP(E56, location!E$2:F$290, 2, FALSE)), "") -> Anguilla Island | G56: East End (Anguilla) | I56: 1 | J56: Anguilla | K56: Anguilla | L56: 8 | M56: Southern America | N56: Anguilla | O56: 1 | P56: =IFERROR(VLOOKUP(E56, location!$E$2:$P$290, 12, FALSE), "") -> Central America and the Caribbean | Q56: North America
A57: 332 | B57: AIA | D57: AI | E57: Anguilla | F57: =IFERROR(IF(VLOOKUP(E57, location!E$2:F$290, 2, FALSE) = 0, "", VLOOKUP(E57, location!E$2:F$290, 2, FALSE)), "") -> Anguilla Island | G57: George Hill | I57: 1 | J57: Anguilla | K57: Anguilla | L57: 8 | M57: Southern America | N57: Anguilla | O57: 1 | P57: =IFERROR(VLOOKUP(E57, location!$E$2:$P$290, 12, FALSE), "") -> Central America and the Caribbean | Q57: North America
A58: 333 | B58: AIA | D58: AI | E58: Anguilla | F58: =IFERROR(IF(VLOOKUP(E58, location!E$2:F$290, 2, FALSE) = 0, "", VLOOKUP(E58, location!E$2:F$290, 2, FALSE)), "") -> Anguilla Island | G58: Island Harbour | I58: 1 | J58: Anguilla | K58: Anguilla | L58: 8 | M58: Southern America | N58: Anguilla | O58: 1 | P58: =IFERROR(VLOOKUP(E58, location!$E$2:$P$290, 12, FALSE), "") -> Central America and the Caribbean | Q58: North America
A59: 334 | B59: AIA | D59: AI | E59: Anguilla | F59: =IFERROR(IF(VLOOKUP(E59, location!E$2:F$290, 2, FALSE) = 0, "", VLOOKUP(E59, location!E$2:F$290, 2, FALSE)), "") -> Anguilla Island | G59: North Hill | I59: 1 | J59: Anguilla | K59: Anguilla | L59: 8 | M59: Southern America | N59: Anguilla | O59: 1 | P59: =IFERROR(VLOOKUP(E59, location!$E$2:$P$290, 12, FALSE), "") -> Central America and the Caribbean | Q59: North America
A60: 335 | B60: AIA | D60: AI | E60: Anguilla | F60: =IFERROR(IF(VLOOKUP(E60, location!E$2:F$290, 2, FALSE) = 0, "", VLOOKUP(E60, location!E$2:F$290, 2, FALSE)), "") -> Anguilla Island | G60: North Side (Anguilla) | I60: 1 | J60: Anguilla | K60: Anguilla | L60: 8 | M60: Southern America | N60: Anguilla | O60: 1 | P60: =IFERROR(VLOOKUP(E60, location!$E$2:$P$290, 12, FALSE), "") -> Central America and the Caribbean | Q60: North America
A61: 336 | B61: AIA | D61: AI | E61: Anguilla | F61: =IFERROR(IF(VLOOKUP(E61, location!E$2:F$290, 2, FALSE) = 0, "", VLOOKUP(E61, location!E$2:F$290, 2, FALSE)), "") -> Anguilla Island | G61: Pricly Pear Cays | I61: 1 | J61: Anguilla | K61: Anguilla | L61: 8 | M61: Southern America | N61: Anguilla | O61: 1 | P61: =IFERROR(VLOOKUP(E61, location!$E$2:$P$290, 12, FALSE), "") -> Central America and the Caribbean | Q61: North America
A62: 337 | B62: AIA | D62: AI | E62: Anguilla | F62: =IFERROR(IF(VLOOKUP(E62, location!E$2:F$290, 2, FALSE) = 0, "", VLOOKUP(E62, location!E$2:F$290, 2, FALSE)), "") -> Anguilla Island | G62: Sandy Ground | I62: 1 | J62: Anguilla | K62: Anguilla | L62: 8 | M62: Southern America | N62: Anguilla | O62: 1 | P62: =IFERROR(VLOOKUP(E62, location!$E$2:$P$290, 12, FALSE), "") -> Central America and the Caribbean | Q62: North America
A63: 338 | B63: AIA | D63: AI | E63: Anguilla | F63: =IFERROR(IF(VLOOKUP(E63, location!E$2:F$290, 2, FALSE) = 0, "", VLOOKUP(E63, location!E$2:F$290, 2, FALSE)), "") -> Anguilla Island | G63: Sandy Hill | I63: 1 | J63: Anguilla | K63: Anguilla | L63: 8 | M63: Southern America | N63: Anguilla | O63: 1 | P63: =IFERROR(VLOOKUP(E63, location!$E$2:$P$290, 12, FALSE), "") -> Central America and the Caribbean | Q63: North America
A64: 339 | B64: AIA | D64: AI | E64: Anguilla | F64: =IFERROR(IF(VLOOKUP(E64, location!E$2:F$290, 2, FALSE) = 0, "", VLOOKUP(E64, location!E$2:F$290, 2, FALSE)), "") -> Anguilla Island | G64: Scrub Island | I64: 1 | J64: Anguilla | K64: Anguilla | L64: 8 | M64: Southern America | N64: Anguilla | O64: 1 | P64: =IFERROR(VLOOKUP(E64, location!$E$2:$P$290, 12, FALSE), "") -> Central America and the Caribbean | Q64: North America
A65: 340 | B65: AIA | D65: AI | E65: Anguilla | F65: =IFERROR(IF(VLOOKUP(E65, location!E$2:F$290, 2, FALSE) = 0, "", VLOOKUP(E65, location!E$2:F$290, 2, FALSE)), "") -> Anguilla Island | G65: Sombrero Island | I65: 1 | J65: Anguilla | K65: Anguilla | L65: 8 | M65: Southern America | N65: Anguilla | O65: 1 | P65: =IFERROR(VLOOKUP(E65, location!$E$2:$P$290, 12, FALSE), "") -> Central America and the Caribbean | Q65: North America
... A71: 346 | B71: AIA | D71: AI | E71: Anguilla | F71: =IFERROR(IF(VLOOKUP(E71, location!E$2:F$290, 2, FALSE) = 0, "", VLOOKUP(E71, location!E$2:F$290, 2, FALSE)), "") -> Anguilla Island | G71: West End | I71: 1 | J71: Anguilla | K71: Anguilla | L71: 8 | M71: Southern America | N71: Anguilla | O71: 1 | P71: =IFERROR(VLOOKUP(E71, location!$E$2:$P$290, 12, FALSE), "") -> Central America and the Caribbean | Q71: North America
A72: 347 | B72: ALA | D72: AX | E72: Åland | F72: =IFERROR(IF(VLOOKUP(E72, location!E$2:F$290, 2, FALSE) = 0, "", VLOOKUP(E72, location!E$2:F$290, 2, FALSE)), "") -> Aland Islands; Åland Islands; �LAND ISLANDS | G72: Archipelago | H72: Archipelago | I72: 1 | J72: Åland | L72: 1 | M72: Europe | O72: 1 | P72: =IFERROR(VLOOKUP(E72, location!$E$2:$P$290, 12, FALSE), "") -> Europe | Q72: Europe
A73: 348 | B73: ALA | D73: AX | E73: Åland | F73: =IFERROR(IF(VLOOKUP(E73, location!E$2:F$290, 2, FALSE) = 0, "", VLOOKUP(E73, location!E$2:F$290, 2, FALSE)), "") -> Aland Islands; Åland Islands; �LAND ISLANDS | G73: Countryside | H73: Countryside | I73: 1 | J73: Åland | L73: 1 | M73: Europe | O73: 1 | P73: =IFERROR(VLOOKUP(E73, location!$E$2:$P$290, 12, FALSE), "") -> Europe | Q73: Europe
A74: 349 | B74: ALA | D74: AX | E74: Åland | F74: =IFERROR(IF(VLOOKUP(E74, location!E$2:F$290, 2, FALSE) = 0, "", VLOOKUP(E74, location!E$2:F$290, 2, FALSE)), "") -> Aland Islands; Åland Islands; �LAND ISLANDS | G74: Mariehamn | H74: Mariehamn | I74: 1 | J74: Åland | L74: 1 | M74: Europe | O74: 1 | P74: =IFERROR(VLOOKUP(E74, location!$E$2:$P$290, 12, FALSE), "") -> Europe | Q74: Europe
A75: 350 | B75: ALB | C75: AL-01 | D75: AL | E75: Albania | F75: =IFERROR(IF(VLOOKUP(E75, location!E$2:F$290, 2, FALSE) = 0, "", VLOOKUP(E75, location!E$2:F$290, 2, FALSE)), "") -> Western Palaearctic Region - Albania | G75: Berat | I75: 0 | J75: Albania | K75: Albania | L75: 1 | M75: Europe | N75: Albania | O75: 1 | P75: =IFERROR(VLOOKUP(E75, location!$E$2:$P$290, 12, FALSE), "") -> Europe | Q75: Europe
A76: 351 | B76: ALB | D76: AL | E76: Albania | F76: =IFERROR(IF(VLOOKUP(E76, location!E$2:F$290, 2, FALSE) = 0, "", VLOOKUP(E76, location!E$2:F$290, 2, FALSE)), "") -> Western Palaearctic Region - Albania | G76: Dibër | H76: Dibra; Dibrë | I76: 0 | J76: Albania | K76: Albania | L76: 1 | M76: Europe | N76: Albania | O76: 1 | P76: =IFERROR(VLOOKUP(E76, location!$E$2:$P$290, 12, FALSE), "") -> Europe | Q76: Europe
A77: 352 | B77: ALB | D77: AL | E77: Albania | F77: =IFERROR(IF(VLOOKUP(E77, location!E$2:F$290, 2, FALSE) = 0, "", VLOOKUP(E77, location!E$2:F$290, 2, FALSE)), "") -> Western Palaearctic Region - Albania | G77: Durrës | H77: Durresi; Durrsi; Durazzo | I77: 0 | J77: Albania | K77: Albania | L77: 1 | M77: Europe | N77: Albania | O77: 1 | P77: =IFERROR(VLOOKUP(E77, location!$E$2:$P$290, 12, FALSE), "") -> Europe | Q77: Europe
A78: 353 | B78: ALB | C78: AL-03 | D78: AL | E78: Albania | F78: =IFERROR(IF(VLOOKUP(E78, location!E$2:F$290, 2, FALSE) = 0, "", VLOOKUP(E78, location!E$2:F$290, 2, FALSE)), "") -> Western Palaearctic Region - Albania | G78: Elbasan | I78: 0 | J78: Albania | K78: Albania | L78: 1 | M78: Europe | N78: Albania | O78: 1 | P78: =IFERROR(VLOOKUP(E78, location!$E$2:$P$290, 12, FALSE), "") -> Europe | Q78: Europe
A79: 354 | B79: ALB | C79: AL-04 | D79: AL | E79: Albania | F79: =IFERROR(IF(VLOOKUP(E79, location!E$2:F$290, 2, FALSE) = 0, "", VLOOKUP(E79, location!E$2:F$290, 2, FALSE)), "") -> Western Palaearctic Region - Albania | G79: Fier | I79: 0 | J79: Albania | K79: Albania | L79: 1 | M79: Europe | N79: Albania | O79: 1 | P79: =IFERROR(VLOOKUP(E79, location!$E$2:$P$290, 12, FALSE), "") -> Europe | Q79: Europe
A80: 355 | B80: ALB | D80: AL | E80: Albania | F80: =IFERROR(IF(VLOOKUP(E80, location!E$2:F$290, 2, FALSE) = 0, "", VLOOKUP(E80, location!E$2:F$290, 2, FALSE)), "") -> Western Palaearctic Region - Albania | G80: Gjirokastër | H80: Gjinokastër; Argirocastro; Argyroc | I80: 0 | J80: Albania | K80: Albania | L80: 1 | M80: Europe | N80: Albania | O80: 1 | P80: =IFERROR(VLOOKUP(E80, location!$E$2:$P$290, 12, FALSE), "") -> Europe | Q80: Europe
A81: 356 | B81: ALB | D81: AL | E81: Albania | F81: =IFERROR(IF(VLOOKUP(E81, location!E$2:F$290, 2, FALSE) = 0, "", VLOOKUP(E81, location!E$2:F$290, 2, FALSE)), "") -> Western Palaearctic Region - Albania | G81: Korçë | H81: Coriza; Corizza; Koritsa; Koritza; K | I81: 0 | J81: Albania | K81: Albania | L81: 1 | M81: Europe | N81: Albania | O81: 1 | P81: =IFERROR(VLOOKUP(E81, location!$E$2:$P$290, 12, FALSE), "") -> Europe | Q81: Europe
A82: 357 | B82: ALB | D82: AL | E82: Albania | F82: =IFERROR(IF(VLOOKUP(E82, location!E$2:F$290, 2, FALSE) = 0, "", VLOOKUP(E82, location!E$2:F$290, 2, FALSE)), "") -> Western Palaearctic Region - Albania | G82: Kukës | H82: Kosova; Kossovo | I82: 0 | J82: Albania | K82: Albania | L82: 1 | M82: Europe | N82: Albania | O82: 1 | P82: =IFERROR(VLOOKUP(E82, location!$E$2:$P$290, 12, FALSE), "") -> Europe | Q82: Europe
A83: 358 | B83: ALB | D83: AL | E83: Albania | F83: =IFERROR(IF(VLOOKUP(E83, location!E$2:F$290, 2, FALSE) = 0, "", VLOOKUP(E83, location!E$2:F$290, 2, FALSE)), "") -> Western Palaearctic Region - Albania | G83: Lezhë | H83: Alessio; Lezha | I83: 0 | J83: Albania | K83: Albania | L83: 1 | M83: Europe | N83: Albania | O83: 1 | P83: =IFERROR(VLOOKUP(E83, location!$E$2:$P$290, 12, FALSE), "") -> Europe | Q83: Europe
A84: 359 | B84: ALB | D84: AL | E84: Albania | F84: =IFERROR(IF(VLOOKUP(E84, location!E$2:F$290, 2, FALSE) = 0, "", VLOOKUP(E84, location!E$2:F$290, 2, FALSE)), "") -> Western Palaearctic Region - Albania | G84: Shkodër | H84: Escútari; Shkodra; Skodë; Scutari | I84: 0 | J84: Albania | K84: Albania | L84: 1 | M84: Europe | N84: Albania | O84: 1 | P84: =IFERROR(VLOOKUP(E84, location!$E$2:$P$290, 12, FALSE), "") -> Europe | Q84: Europe
A85: 360 | B85: ALB | D85: AL | E85: Albania | F85: =IFERROR(IF(VLOOKUP(E85, location!E$2:F$290, 2, FALSE) = 0, "", VLOOKUP(E85, location!E$2:F$290, 2, FALSE)), "") -> Western Palaearctic Region - Albania | G85: Tiranë | H85: Tiran; Tirana | I85: 0 | J85: Albania | K85: Albania | L85: 1 | M85: Europe | N85: Albania | O85: 1 | P85: =IFERROR(VLOOKUP(E85, location!$E$2:$P$290, 12, FALSE), "") -> Europe | Q85: Europe
A86: 361 | B86: ALB | D86: AL | E86: Albania | F86: =IFERROR(IF(VLOOKUP(E86, location!E$2:F$290, 2, FALSE) = 0, "", VLOOKUP(E86, location!E$2:F$290, 2, FALSE)), "") -> Western Palaearctic Region - Albania | G86: Vlorë | H86: Vlona; Vlora; Vlonë; Valona | I86: 0 | J86: Albania | K86: Albania | L86: 1 | M86: Europe | N86: Albania | O86: 1 | P86: =IFERROR(VLOOKUP(E86, location!$E$2:$P$290, 12, FALSE), "") -> Europe | Q86: Europe
A87: 362 | B87: AND | C87: AD-07 | D87: AD | E87: Andorra | F87: =IFERROR(IF(VLOOKUP(E87, location!E$2:F$290, 2, FALSE) = 0, "", VLOOKUP(E87, location!E$2:F$290, 2, FALSE)), "") | G87: Andorra la Vella | I87: 0 | J87: Andorra | M87: Europe | O87: 1 | P87: =IFERROR(VLOOKUP(E87, location!$E$2:$P$290, 12, FALSE), "") -> Europe | Q87: Europe
A88: 363 | B88: AND | C88: AD-02 | D88: AD | E88: Andorra | F88: =IFERROR(IF(VLOOKUP(E88, location!E$2:F$290, 2, FALSE) = 0, "", VLOOKUP(E88, location!E$2:F$290, 2, FALSE)), "") | G88: Canillo | I88: 0 | J88: Andorra | M88: Europe | O88: 1 | P88: =IFERROR(VLOOKUP(E88, location!$E$2:$P$290, 12, FALSE), "") -> Europe | Q88: Europe
A89: 364 | B89: AND | C89: AD-03 | D89: AD | E89: Andorra | F89: =IFERROR(IF(VLOOKUP(E89, location!E$2:F$290, 2, FALSE) = 0, "", VLOOKUP(E89, location!E$2:F$290, 2, FALSE)), "") | G89: Encamp | I89: 0 | J89: Andorra | M89: Europe | O89: 1 | P89: =IFERROR(VLOOKUP(E89, location!$E$2:$P$290, 12, FALSE), "") -> Europe | Q89: Europe
A90: 365 | B90: AND | C90: AD-08 | D90: AD | E90: Andorra | F90: =IFERROR(IF(VLOOKUP(E90, location!E$2:F$290, 2, FALSE) = 0, "", VLOOKUP(E90, location!E$2:F$290, 2, FALSE)), "") | G90: Escaldes-Engordany | I90: 0 | J90: Andorra | M90: Europe | O90: 1 | P90: =IFERROR(VLOOKUP(E90, location!$E$2:$P$290, 12, FALSE), "") -> Europe | Q90: Europe
A91: 366 | B91: AND | C91: AD-04 | D91: AD | E91: Andorra | F91: =IFERROR(IF(VLOOKUP(E91, location!E$2:F$290, 2, FALSE) = 0, "", VLOOKUP(E91, location!E$2:F$290, 2, FALSE)), "") | G91: La Massana | I91: 0 | J91: Andorra | M91: Europe | O91: 1 | P91: =IFERROR(VLOOKUP(E91, location!$E$2:$P$290, 12, FALSE), "") -> Europe | Q91: Europe
A92: 367 | B92: AND | C92: AD-05 | D92: AD | E92: Andorra | F92: =IFERROR(IF(VLOOKUP(E92, location!E$2:F$290, 2, FALSE) = 0, "", VLOOKUP(E92, location!E$2:F$290, 2, FALSE)), "") | G92: Ordino | I92: 0 | J92: Andorra | M92: Europe | O92: 1 | P92: =IFERROR(VLOOKUP(E92, location!$E$2:$P$290, 12, FALSE), "") -> Europe | Q92: Europe
A93: 368 | B93: AND | D93: AD | E93: Andorra | F93: =IFERROR(IF(VLOOKUP(E93, location!E$2:F$290, 2, FALSE) = 0, "", VLOOKUP(E93, location!E$2:F$290, 2, FALSE)), "") | G93: Sant Julià de Lòria | I93: 0 | J93: Andorra | M93: Europe | O93: 1 | P93: =IFERROR(VLOOKUP(E93, location!$E$2:$P$290, 12, FALSE), "") -> Europe | Q93: Europe
A94: 369 | B94: ARE | D94: AE | E94: United Arab Emirates | F94: =IFERROR(IF(VLOOKUP(E94, location!E$2:F$290, 2, FALSE) = 0, "", VLOOKUP(E94, location!E$2:F$290, 2, FALSE)), "") -> United Arab Em.; the United Arab Emirates | G94: Abu Dhabi | I94: 0 | J94: United Arab Emirates | K94: United Arab Emirates | L94: 3 | M94: Asia-Temperate | N94: United Arab Emirates (the) | O94: 1 | P94: =IFERROR(VLOOKUP(E94, location!$E$2:$P$290, 12, FALSE), "") -> Saharo-Arabia | Q94: Asia
A95: 370 | B95: ARE | D95: AE | E95: United Arab Emirates | F95: =IFERROR(IF(VLOOKUP(E95, location!E$2:F$290, 2, FALSE) = 0, "", VLOOKUP(E95, location!E$2:F$290, 2, FALSE)), "") -> United Arab Em.; the United Arab Emirates | G95: Ajman | I95: 0 | J95: United Arab Emirates | K95: United Arab Emirates | L95: 3 | M95: Asia-Temperate | N95: United Arab Emirates (the) | O95: 1 | P95: =IFERROR(VLOOKUP(E95, location!$E$2:$P$290, 12, FALSE), "") -> Saharo-Arabia | Q95: Asia
A96: 371 | B96: ARE | D96: AE | E96: United Arab Emirates | F96: =IFERROR(IF(VLOOKUP(E96, location!E$2:F$290, 2, FALSE) = 0, "", VLOOKUP(E96, location!E$2:F$290, 2, FALSE)), "") -> United Arab Em.; the United Arab Emirates | G96: Dubai | I96: 0 | J96: United Arab Emirates | K96: United Arab Emirates | L96: 3 | M96: Asia-Temperate | N96: United Arab Emirates (the) | O96: 1 | P96: =IFERROR(VLOOKUP(E96, location!$E$2:$P$290, 12, FALSE), "") -> Saharo-Arabia | Q96: Asia
A97: 372 | B97: ARE | D97: AE | E97: United Arab Emirates | F97: =IFERROR(IF(VLOOKUP(E97, location!E$2:F$290, 2, FALSE) = 0, "", VLOOKUP(E97, location!E$2:F$290, 2, FALSE)), "") -> United Arab Em.; the United Arab Emirates | G97: Fujairah | I97: 0 | J97: United Arab Emirates | K97: United Arab Emirates | L97: 3 | M97: Asia-Temperate | N97: United Arab Emirates (the) | O97: 1 | P97: =IFERROR(VLOOKUP(E97, location!$E$2:$P$290, 12, FALSE), "") -> Saharo-Arabia | Q97: Asia
A98: 373 | B98: ARE | D98: AE | E98: United Arab Emirates | F98: =IFERROR(IF(VLOOKUP(E98, location!E$2:F$290, 2, FALSE) = 0, "", VLOOKUP(E98, location!E$2:F$290, 2, FALSE)), "") -> United Arab Em.; the United Arab Emirates | G98: Ras Al-Khaimah | I98: 0 | J98: United Arab Emirates | K98: United Arab Emirates | L98: 3 | M98: Asia-Temperate | N98: United Arab Emirates (the) | O98: 1 | P98: =IFERROR(VLOOKUP(E98, location!$E$2:$P$290, 12, FALSE), "") -> Saharo-Arabia | Q98: Asia
A99: 374 | B99: ARE | D99: AE | E99: United Arab Emirates | F99: =IFERROR(IF(VLOOKUP(E99, location!E$2:F$290, 2, FALSE) = 0, "", VLOOKUP(E99, location!E$2:F$290, 2, FALSE)), "") -> United Arab Em.; the United Arab Emirates | G99: Sharjah | I99: 0 | J99: United Arab Emirates | K99: United Arab Emirates | L99: 3 | M99: Asia-Temperate | N99: United Arab Emirates (the) | O99: 1 | P99: =IFERROR(VLOOKUP(E99, location!$E$2:$P$290, 12, FALSE), "") -> Saharo-Arabia | Q99: Asia
A100: 375 | B100: ARE | D100: AE | E100: United Arab Emirates | F100: =IFERROR(IF(VLOOKUP(E100, location!E$2:F$290, 2, FALSE) = 0, "", VLOOKUP(E100, location!E$2:F$290, 2, FALSE)), "") -> United Arab Em.; the United Arab Emirates | G100: Umm al-Qaywayn | I100: 0 | J100: United Arab Emirates | K100: United Arab Emirates | L100: 3 | M100: Asia-Temperate | N100: United Arab Emirates (the) | O100: 1 | P100: =IFERROR(VLOOKUP(E100, location!$E$2:$P$290, 12, FALSE), "") -> Saharo-Arabia | Q100: Asia
A101: 376 | B101: ARG | C101: AR-B | D101: AR | E101: Argentina | F101: =IFERROR(IF(VLOOKUP(E101, location!E$2:F$290, 2, FALSE) = 0, "", VLOOKUP(E101, location!E$2:F$290, 2, FALSE)), "") -> Argentina Distrito Federal; Argentina Northeast; Argentina Northwest; Argentina South; Argentine | G101: Buenos Aires | H101: Baires; Buenos Ayres | I101: 0 | J101: Argentina | L101: 8 | M101: Southern America | N101: Argentina | O101: 1 | P101: =IFERROR(VLOOKUP(E101, location!$E$2:$P$290, 12, FALSE), "") -> Southern America | Q101: South America
A102: 377 | B102: ARG | C102: AR-K | D102: AR | E102: Argentina | F102: =IFERROR(IF(VLOOKUP(E102, location!E$2:F$290, 2, FALSE) = 0, "", VLOOKUP(E102, location!E$2:F$290, 2, FALSE)), "") -> Argentina Distrito Federal; Argentina Northeast; Argentina Northwest; Argentina South; Argentine | G102: Catamarca | I102: 0 | J102: Argentina | L102: 8 | M102: Southern America | N102: Argentina | O102: 1 | P102: =IFERROR(VLOOKUP(E102, location!$E$2:$P$290, 12, FALSE), "") -> Southern America | Q102: South America
A103: 378 | B103: ARG | C103: AR-H | D103: AR | E103: Argentina | F103: =IFERROR(IF(VLOOKUP(E103, location!E$2:F$290, 2, FALSE) = 0, "", VLOOKUP(E103, location!E$2:F$290, 2, FALSE)), "") -> Argentina Distrito Federal; Argentina Northeast; Argentina Northwest; Argentina South; Argentine | G103: Chaco | H103: El Chaco; Presidente Juan Peron | I103: 0 | J103: Argentina | L103: 8 | M103: Southern America | N103: Argentina | O103: 1 | P103: =IFERROR(VLOOKUP(E103, location!$E$2:$P$290, 12, FALSE), "") -> Southern America | Q103: South America
A104: 379 | B104: ARG | C104: AR-U | D104: AR | E104: Argentina | F104: =IFERROR(IF(VLOOKUP(E104, location!E$2:F$290, 2, FALSE) = 0, "", VLOOKUP(E104, location!E$2:F$290, 2, FALSE)), "") -> Argentina Distrito Federal; Argentina Northeast; Argentina Northwest; Argentina South; Argentine | G104: Chubut | I104: 0 | J104: Argentina | L104: 8 | M104: Southern America | N104: Argentina | O104: 1 | P104: =IFERROR(VLOOKUP(E104, location!$E$2:$P$290, 12, FALSE), "") -> Southern America | Q104: South America
A105: 380 | B105: ARG | D105: AR | E105: Argentina | F105: =IFERROR(IF(VLOOKUP(E105, location!E$2:F$290, 2, FALSE) = 0, "", VLOOKUP(E105, location!E$2:F$290, 2, FALSE)), "") -> Argentina Distrito Federal; Argentina Northeast; Argentina Northwest; Argentina South; Argentine | G105: Ciudad de Buenos Aires | H105: BUENOS AIRES D.F.; Capital Federa | I105: 0 | J105: Argentina | L105: 8 | M105: Southern America | N105: Argentina | O105: 1 | P105: =IFERROR(VLOOKUP(E105, location!$E$2:$P$290, 12, FALSE), "") -> Southern America | Q105: South America
...
